MatplotlibYonghuZhinan/README.md
MatplotlibYonghuZhinan/__init__.py
MatplotlibYonghuZhinan/__main__.py
MatplotlibYonghuZhinan/file.epub
MatplotlibYonghuZhinan/index.html
MatplotlibYonghuZhinan/css/__init__.py
MatplotlibYonghuZhinan/css/annotations.css
MatplotlibYonghuZhinan/css/main.css
MatplotlibYonghuZhinan/css/normalize.css
MatplotlibYonghuZhinan/css/popup.css
MatplotlibYonghuZhinan/font/__init__.py
MatplotlibYonghuZhinan/font/fontello.eot
MatplotlibYonghuZhinan/font/fontello.svg
MatplotlibYonghuZhinan/font/fontello.ttf
MatplotlibYonghuZhinan/font/fontello.woff
MatplotlibYonghuZhinan/img/__init__.py
MatplotlibYonghuZhinan/img/annotator-glyph-sprite.png
MatplotlibYonghuZhinan/img/annotator-icon-sprite.png
MatplotlibYonghuZhinan/img/apple-touch-icon.png
MatplotlibYonghuZhinan/img/cancelfullscreen.png
MatplotlibYonghuZhinan/img/close.png
MatplotlibYonghuZhinan/img/fullscreen.png
MatplotlibYonghuZhinan/img/loader.gif
MatplotlibYonghuZhinan/img/menu-icon.png
MatplotlibYonghuZhinan/img/save.png
MatplotlibYonghuZhinan/img/saved.png
MatplotlibYonghuZhinan/img/settings-s.png
MatplotlibYonghuZhinan/img/settings.png
MatplotlibYonghuZhinan/img/star.png
MatplotlibYonghuZhinan/js/__init__.py
MatplotlibYonghuZhinan/js/epub.js
MatplotlibYonghuZhinan/js/epub.min.js
MatplotlibYonghuZhinan/js/epub.min.map
MatplotlibYonghuZhinan/js/hooks.min.js
MatplotlibYonghuZhinan/js/hooks.min.map
MatplotlibYonghuZhinan/js/reader.js
MatplotlibYonghuZhinan/js/reader.js.map
MatplotlibYonghuZhinan/js/reader.min.js
MatplotlibYonghuZhinan/js/reader.min.map
MatplotlibYonghuZhinan/js/hooks/__init__.py
MatplotlibYonghuZhinan/js/hooks/extensions/__init__.py
MatplotlibYonghuZhinan/js/hooks/extensions/highlight.js
MatplotlibYonghuZhinan/js/libs/__init__.py
MatplotlibYonghuZhinan/js/libs/jquery.min.js
MatplotlibYonghuZhinan/js/libs/localforage.min.js
MatplotlibYonghuZhinan/js/libs/screenfull.js
MatplotlibYonghuZhinan/js/libs/screenfull.min.js
MatplotlibYonghuZhinan/js/libs/zip.min.js
matplotlib_yonghu_zhinan-2024.3.2.0.dist-info/METADATA
matplotlib_yonghu_zhinan-2024.3.2.0.dist-info/WHEEL
matplotlib_yonghu_zhinan-2024.3.2.0.dist-info/entry_points.txt
matplotlib_yonghu_zhinan-2024.3.2.0.dist-info/top_level.txt
matplotlib_yonghu_zhinan-2024.3.2.0.dist-info/RECORD
